pyrisks_grf/A_ESTRUCTURA.py
pyrisks_grf/A_TRANSVERSAL.py
pyrisks_grf/ML_01_VaR.py
pyrisks_grf/ML_02_PLANO.py
pyrisks_grf/ML_03_OPERACIONES_H_PAN.py
pyrisks_grf/ML_04_OPERACIONES_BLOTTER.py
pyrisks_grf/MN_01_METRICAS.py
pyrisks_grf/MN_02_IRL.py
pyrisks_grf/MN_03_INFOMERCADO.py
pyrisks_grf/Z_TESTING_L.py
pyrisks_grf/Z_TESTING_N.py
pyrisks_grf/__init__.py
pyrisks_grf/module1.py
pyrisks_grf/module2.py
risk_package_grf-0.0.14.dist-info/METADATA
risk_package_grf-0.0.14.dist-info/WHEEL
risk_package_grf-0.0.14.dist-info/top_level.txt
risk_package_grf-0.0.14.dist-info/RECORD
