Metadata-Version: 2.1
Name: risk_package_grf
Version: 0.0.14
Summary: This is the first version of GRF package for Panama.
Author: Mateo Rodriguez, Gerencias de Riesgos Financieros Corredores Davivienda S.A.
Author-email: marodriguezr@corredores.com , gerenciaderiesgos@corredores.com
Requires-Dist: datetime
Requires-Dist: gcsfs
Requires-Dist: google
Requires-Dist: google-auth
Requires-Dist: google-cloud
Requires-Dist: google-cloud-bigquery
Requires-Dist: google-cloud-storage
Requires-Dist: IPython
Requires-Dist: ipywidgets
Requires-Dist: networkx
Requires-Dist: numpy
Requires-Dist: openpyxl
Requires-Dist: pandas
Requires-Dist: QuantLib
Requires-Dist: scipy
Requires-Dist: tk
